dummy_project/__init__.py
dummy_project/core.py
dummy_project_swayam-0.1.0.dist-info/licenses/LICENSE
dummy_project_swayam-0.1.0.dist-info/METADATA
dummy_project_swayam-0.1.0.dist-info/WHEEL
dummy_project_swayam-0.1.0.dist-info/top_level.txt
dummy_project_swayam-0.1.0.dist-info/RECORD
