Metadata-Version: 2.4
Name: dummy-project-swayam
Version: 0.1.0
Summary: A simple dummy project for testing trusted publishing
Author-email: SwayamInSync <singhswayam008@example.com>
Project-URL: Homepage, https://github.com/SwayamInSync/Dummy_Project
Project-URL: Repository, https://github.com/SwayamInSync/Dummy_Project
Classifier: Development Status :: 3 - Alpha
Classifier: Intended Audience :: Developers
Classifier: License :: OSI Approved :: MIT License
Classifier: Programming Language :: Python :: 3
Classifier: Programming Language :: Python :: 3.8
Classifier: Programming Language :: Python :: 3.9
Classifier: Programming Language :: Python :: 3.10
Classifier: Programming Language :: Python :: 3.11
Classifier: Programming Language :: Python :: 3.12
Requires-Python: >=3.8
License-File: LICENSE
Dynamic: license-file
